{
  "id": "camp-012",
  "language": "ru",
  "seo_title": "Campingaz Газовая плита 2-конфорочная - Мощная и Компактная",
  "meta_description": "Campingaz Газовая плита 2-конфорочная - Мощная и Компактная: 2 независимых горелки, пьезо-розжиг, встроенный ветровой щит.",
  "alt_text": "Campingaz Газовая плита 2-конфорочная — Мощная и Компактная",
  "pinterest_title": "Campingaz Газовая плита 2-конфорочная - Мощная и Компактная для кемпинга 🏕️",
  "pinterest_description": "Campingaz Газовая плита 2-конфорочная - Мощная и Компактная от Campingaz: полезное решение для кемпинга, активного отдыха и выходных. Сохрани эту находку для своей следующей поездки.",
  "hashtags": [
    "#кемпинг",
    "#активныйотдых",
    "#кемпингоборудование"
  ],
  "source": "localized_from_de_v1"
}
